window_terminal/__init__.py
window_terminal-1.0.6.dist-info/LICENSE
window_terminal-1.0.6.dist-info/METADATA
window_terminal-1.0.6.dist-info/WHEEL
window_terminal-1.0.6.dist-info/top_level.txt
window_terminal-1.0.6.dist-info/RECORD
