Metadata-Version: 2.1
Name: window-terminal
Version: 1.0.6
Summary: Start new Terminal Windows with print and input control
Home-page: https://github.com/Igorxp5/window-terminal
Author: Igor Fernandes (Igorxp5)
Author-email: rogixp5@gmail.com
License: MIT
Platform: UNKNOWN
Classifier: Programming Language :: Python :: 3
Classifier: License :: OSI Approved :: MIT License
Classifier: Operating System :: OS Independent
Requires-Python: >=3.6
